rankflow-0.1.4.dist-info/METADATA
rankflow-0.1.4.dist-info/WHEEL
rankflow-0.1.4.dist-info/licenses/LICENSE
rankflow/__init__.py
rankflow/_version.py
rankflow/main.py
rankflow-0.1.4.dist-info/RECORD
