Metadata-Version: 2.1
Name: rankflow
Version: 0.1.4
Summary: Plot how multiple ranks evolved over processing steps - draw a rankflow.
Keywords: rankflow,rank,flow,plot,RAG,retriever,evaluation,rag-evaluation,rag-eval,rag-eval-plot,rag-evaluation-plot
Author-Email: Krystian Safjan <ksafjan@gmail.com>
License: MIT
Classifier: Development Status :: 3 - Alpha
Classifier: Intended Audience :: Developers
Classifier: Intended Audience :: Science/Research
Classifier: License :: OSI Approved :: MIT License
Classifier: Programming Language :: Python :: 3
Classifier: Topic :: Software Development :: Libraries :: Python Modules
Classifier: Topic :: Utilities
Classifier: Topic :: Scientific/Engineering
Classifier: Topic :: Scientific/Engineering :: Information Analysis
Classifier: Topic :: Scientific/Engineering :: Artificial Intelligence
Classifier: Topic :: Scientific/Engineering :: Visualization
Classifier: Topic :: Scientific/Engineering :: Mathematics
Project-URL: Source, https://github.com/izikeros/rankflow
Project-URL: Bug tracker, https://github.com/izikeros/rankflow/issues
Requires-Python: >=3.9
Requires-Dist: matplotlib>=3.9.0
Requires-Dist: numpy>=1.26.4
Requires-Dist: pandas; extra == "socks"
Provides-Extra: socks
